README.md
setup.py
asposediagramcloud/__init__.py
asposediagramcloud/api_client.py
asposediagramcloud/configuration.py
asposediagramcloud/rest.py
asposediagramcloud.egg-info/PKG-INFO
asposediagramcloud.egg-info/SOURCES.txt
asposediagramcloud.egg-info/dependency_links.txt
asposediagramcloud.egg-info/requires.txt
asposediagramcloud.egg-info/top_level.txt
asposediagramcloud/apis/__init__.py
asposediagramcloud/apis/diagram_api.py
asposediagramcloud/apis/o_auth_api.py
asposediagramcloud/apis/storage_api.py
asposediagramcloud/models/__init__.py
asposediagramcloud/models/access_token_response.py
asposediagramcloud/models/api_response_of_list_of_page_data.py
asposediagramcloud/models/create_new_response.py
asposediagramcloud/models/diagram_save_options.py
asposediagramcloud/models/disc_usage.py
asposediagramcloud/models/draw_shape_data.py
asposediagramcloud/models/ellipse_data.py
asposediagramcloud/models/error.py
asposediagramcloud/models/error_details.py
asposediagramcloud/models/file_version.py
asposediagramcloud/models/file_versions.py
asposediagramcloud/models/files_list.py
asposediagramcloud/models/files_upload_result.py
asposediagramcloud/models/html_save_options.py
asposediagramcloud/models/image_save_options.py
asposediagramcloud/models/line_data.py
asposediagramcloud/models/modify_response.py
asposediagramcloud/models/object_exist.py
asposediagramcloud/models/page_data.py
asposediagramcloud/models/page_setting.py
asposediagramcloud/models/page_size.py
asposediagramcloud/models/pdf_digital_signature_details.py
asposediagramcloud/models/pdf_encryption_details.py
asposediagramcloud/models/pdf_save_options.py
asposediagramcloud/models/point_f.py
asposediagramcloud/models/polyline_data.py
asposediagramcloud/models/rectangle_f.py
asposediagramcloud/models/rendering_save_options.py
asposediagramcloud/models/saa_spose_response.py
asposediagramcloud/models/save_as_response.py
asposediagramcloud/models/save_options_model.py
asposediagramcloud/models/save_options_request.py
asposediagramcloud/models/shape_data.py
asposediagramcloud/models/shape_style_data.py
asposediagramcloud/models/storage_exist.py
asposediagramcloud/models/storage_file.py
